sycavision/sycacolor.py
sycavision/sycaregister.py
sycavision/sycashape.py
sycavision/sycavision.py
sycavision-3.0.dist-info/METADATA
sycavision-3.0.dist-info/WHEEL
sycavision-3.0.dist-info/entry_points.txt
sycavision-3.0.dist-info/license.txt
sycavision-3.0.dist-info/top_level.txt
sycavision-3.0.dist-info/RECORD
