Metadata-Version: 2.1
Name: sycavision
Version: 3.0
Summary: Image processing library for FRC teams.
Home-page: https://github.com/enisgetmez/sycavision
Author: Enis Getmez
Author-email: enis@enisgetmez.com
License: MIT
Platform: UNKNOWN
Classifier: License :: OSI Approved :: MIT License
Classifier: Programming Language :: Python :: 3
Classifier: Programming Language :: Python :: 3.6
Classifier: Programming Language :: Python :: 3.7
Requires-Dist: pynetworktables
Requires-Dist: numpy
Requires-Dist: argparse
Requires-Dist: imutils
Requires-Dist: opencv-python
Requires-Dist: pyfiglet
